LICENSE.pdf
MANIFEST.in
README.md
setup.py
aps/__init__.py
aps/wavepy2/__init__.py
aps/wavepy2/tools/__init__.py
aps/wavepy2/tools/__main__.py
aps/wavepy2/tools/common/__init__.py
aps/wavepy2/tools/common/physical_properties.py
aps/wavepy2/tools/common/wavepy_data.py
aps/wavepy2/tools/common/wavepy_script.py
aps/wavepy2/tools/common/bl/__init__.py
aps/wavepy2/tools/common/bl/crop_image.py
aps/wavepy2/tools/common/bl/grating_interferometry.py
aps/wavepy2/tools/common/bl/surface_from_grad.py
aps/wavepy2/tools/common/widgets/__init__.py
aps/wavepy2/tools/common/widgets/colorbar_crop_widget.py
aps/wavepy2/tools/common/widgets/crop_widget.py
aps/wavepy2/tools/common/widgets/error_integration_widget.py
aps/wavepy2/tools/common/widgets/extract_harmonic_plot_widget.py
aps/wavepy2/tools/common/widgets/figure_slide_colorbar.py
aps/wavepy2/tools/common/widgets/graphical_roi_idx.py
aps/wavepy2/tools/common/widgets/graphical_select_point_idx.py
aps/wavepy2/tools/common/widgets/harmonic_grid_plot_widget.py
aps/wavepy2/tools/common/widgets/harmonic_peak_plot_widget.py
aps/wavepy2/tools/common/widgets/image_to_change.py
aps/wavepy2/tools/common/widgets/plot_dark_field_widget.py
aps/wavepy2/tools/common/widgets/plot_integration_widget.py
aps/wavepy2/tools/common/widgets/plot_intensities_harms_widget.py
aps/wavepy2/tools/common/widgets/plot_profile_widget.py
aps/wavepy2/tools/common/widgets/show_cropped_figure_widget.py
aps/wavepy2/tools/common/widgets/simple_plot_widget.py
aps/wavepy2/tools/common/widgets/single_grating_harmonic_images_widget.py
aps/wavepy2/tools/diagnostic/__init__.py
aps/wavepy2/tools/diagnostic/coherence/__init__.py
aps/wavepy2/tools/diagnostic/coherence/bl/__init__.py
aps/wavepy2/tools/diagnostic/coherence/bl/single_grating_coherence_z_scan.py
aps/wavepy2/tools/diagnostic/coherence/scripts/__init__.py
aps/wavepy2/tools/diagnostic/coherence/scripts/main_single_grating_coherence_z_scan.py
aps/wavepy2/tools/diagnostic/coherence/widgets/__init__.py
wavepy2.egg-info/PKG-INFO
wavepy2.egg-info/SOURCES.txt
wavepy2.egg-info/dependency_links.txt
wavepy2.egg-info/namespace_packages.txt
wavepy2.egg-info/not-zip-safe
wavepy2.egg-info/requires.txt
wavepy2.egg-info/top_level.txt