Metadata-Version: 2.1
Name: wavepy2
Version: 1.0.5
Summary: Wavepy 2 library
Home-page: https://github.com/aps-xsd-opt-group/wavepy2
Download-URL: https://github.com/aps-xsd-opt-group/wavepy2
Author: Luca Rebuffi, Xianbo Shi, Zhi Qiao
Author-email: lrebuffi@anl.gov
Maintainer: XSD-OPT Group @ APS-ANL
Maintainer-email: lrebuffi@anl.gov
License: BSD-3
Keywords: dictionary,glossary,synchrotronsimulation
Classifier: Development Status :: 4 - Beta
Classifier: License :: OSI Approved :: BSD License
Classifier: Natural Language :: English
Classifier: Environment :: Console
Classifier: Environment :: Plugins
Classifier: Programming Language :: Python :: 3.7
Classifier: Topic :: Scientific/Engineering :: Visualization
Classifier: Intended Audience :: Science/Research
